git_split_commit/__init__.py
git_split_commit/command.py
git_split_commit-0.2.0.dist-info/LICENSE.txt
git_split_commit-0.2.0.dist-info/METADATA
git_split_commit-0.2.0.dist-info/WHEEL
git_split_commit-0.2.0.dist-info/entry_points.txt
git_split_commit-0.2.0.dist-info/top_level.txt
git_split_commit-0.2.0.dist-info/RECORD
