Metadata-Version: 2.1
Name: git-split-commit
Version: 0.2.0
Summary: UNKNOWN
Home-page: UNKNOWN
Author: UNKNOWN
Author-email: UNKNOWN
License: UNKNOWN
Platform: UNKNOWN
Requires-Dist: click
Requires-Dist: coloredlogs
Requires-Dist: gitpython
Requires-Dist: simple-term-menu
